beluga_py/__init__.py
beluga_py/api.py
beluga_py/cli.py
beluga_py/exceptions.py
beluga_py-1.0.0.dist-info/DESCRIPTION.rst
beluga_py-1.0.0.dist-info/METADATA
beluga_py-1.0.0.dist-info/RECORD
beluga_py-1.0.0.dist-info/WHEEL
beluga_py-1.0.0.dist-info/entry_points.txt
beluga_py-1.0.0.dist-info/metadata.json
beluga_py-1.0.0.dist-info/top_level.txt
