Metadata-Version: 2.0
Name: beluga-py
Version: 1.0.0
Summary: API & command-line client for BelugaCDN's API.
Home-page: https://github.com/jaddison/beluga_py
Author: James Addison
Author-email: addi00+github.com@gmail.com
License: BSD
Platform: UNKNOWN
Classifier: Development Status :: 4 - Beta
Classifier: Intended Audience :: Developers
Classifier: Programming Language :: Python :: 2
Classifier: Programming Language :: Python :: 2.7
Classifier: Programming Language :: Python :: 3
Classifier: Programming Language :: Python :: 3.3
Classifier: Programming Language :: Python :: 3.4
Classifier: Programming Language :: Python :: 3.5
Classifier: Programming Language :: Python :: 3.6
Requires-Dist: requests
Requires-Dist: six
